pygmailcleaner/__init__.py
pygmailcleaner/main.py
pygmailcleaner/utils/__init__.py
pygmailcleaner/utils/cli.py
pygmailcleaner/utils/commands.py
pygmailcleaner/utils/formatting.py
pygmailcleaner/utils/smpt.py
pygmailcleaner/utils/testing.py
pygmailcleaner-0.1.1.dist-info/METADATA
pygmailcleaner-0.1.1.dist-info/WHEEL
pygmailcleaner-0.1.1.dist-info/entry_points.txt
pygmailcleaner-0.1.1.dist-info/RECORD
