Metadata-Version: 2.1
Name: pygmailcleaner
Version: 0.1.1
Summary: A tool to clear out your gmail inbox
License: MIT
Author: Rupert Arup
Author-email: rupertarup@gmail.com
Requires-Python: >=3.9,<4.0
Classifier: License :: OSI Approved :: MIT License
Classifier: Programming Language :: Python :: 3
Classifier: Programming Language :: Python :: 3.9
Classifier: Programming Language :: Python :: 3.10
Classifier: Programming Language :: Python :: 3.11
Classifier: Programming Language :: Python :: 3.12
Requires-Dist: colorama (>=0.4.6,<0.5.0)
